audio_encoders_pytorch/__init__.py
audio_encoders_pytorch/modules.py
audio_encoders_pytorch/pipelines.py
audio_encoders_pytorch/utils.py
audio_encoders_pytorch-0.0.22.dist-info/LICENSE
audio_encoders_pytorch-0.0.22.dist-info/METADATA
audio_encoders_pytorch-0.0.22.dist-info/WHEEL
audio_encoders_pytorch-0.0.22.dist-info/top_level.txt
audio_encoders_pytorch-0.0.22.dist-info/RECORD
