Metadata-Version: 2.1
Name: audio-encoders-pytorch
Version: 0.0.22
Summary: Audio Encoders - PyTorch
Home-page: https://github.com/archinetai/audio-encoders-pytorch
Author: Flavio Schneider
Author-email: archinetai@protonmail.com
License: MIT
Keywords: artificial intelligence,deep learning,audio
Classifier: Development Status :: 4 - Beta
Classifier: Intended Audience :: Developers
Classifier: Topic :: Scientific/Engineering :: Artificial Intelligence
Classifier: License :: OSI Approved :: MIT License
Classifier: Programming Language :: Python :: 3.6
License-File: LICENSE
Requires-Dist: torch (>=1.6)
Requires-Dist: torchaudio
Requires-Dist: data-science-types (>=0.2)
Requires-Dist: einops (>=0.6)
Requires-Dist: einops-exts (>=0.0.3)
